pyfivbvis/__init__.py
pyfivbvis/vis_fetcher.py
pyfivbvis-0.1.2.dist-info/METADATA
pyfivbvis-0.1.2.dist-info/WHEEL
pyfivbvis-0.1.2.dist-info/entry_points.txt
pyfivbvis-0.1.2.dist-info/top_level.txt
pyfivbvis-0.1.2.dist-info/RECORD
