Metadata-Version: 2.1
Name: pyfivbvis
Version: 0.1.2
Summary: A Python package to fetch data from FIVB VIS
Home-page: https://github.com/openvolley/pyfivbvis
Author: Tyler Widdison
Author-email: tylerperrywiddison@gmail.com
Classifier: Programming Language :: Python :: 3
Classifier: License :: OSI Approved :: MIT License
Classifier: Operating System :: OS Independent
Requires-Python: >=3.6
Requires-Dist: requests
Requires-Dist: beautifulsoup4
